{"assets":{"F99111D3C439758D4F9FFAA8EE22F8D5":{"type":"texture","index":156,"assetRequest":{"type":"slide","state":"incoming-reflection","slide":"B8503B93-F3A5-4410-BAB5-20EC01F385C1"},"url":"assets/F99111D3C439758D4F9FFAA8EE22F8D5.svg","width":1024,"height":576},"8E23504498D2CB49AC5BDD729BEB3B61":{"type":"texture","index":152,"assetRequest":{"type":"slide","state":"contents","slide":"F2C07866-FAE6-40C8-AA5A-CEA6FC6F3CAA"},"url":"assets/8E23504498D2CB49AC5BDD729BEB3B61.svg","width":705,"height":43},"B653AF1AB0499FFDC5457C5AA168816F":{"type":"texture","index":151,"assetRequest":{"type":"slide","state":"contents","slide":"F2C07866-FAE6-40C8-AA5A-CEA6FC6F3CAA"},"url":"assets/B653AF1AB0499FFDC5457C5AA168816F.svg","width":376,"height":62},"D26118405F285ECE109EB9C3B52B2A31":{"type":"texture","index":153,"assetRequest":{"type":"slide","state":"contents","slide":"F2C07866-FAE6-40C8-AA5A-CEA6FC6F3CAA"},"url":"assets/D26118405F285ECE109EB9C3B52B2A31.svg","width":777,"height":44},"5C5CA35AF699D3D54CAEBA3659D3D590":{"type":"texture","index":150,"assetRequest":{"type":"slide","state":"contents","slide":"F2C07866-FAE6-40C8-AA5A-CEA6FC6F3CAA"},"url":"assets/5C5CA35AF699D3D54CAEBA3659D3D590.svg","width":746,"height":77},"7055B3A55E23A029736BDFE481D0DA87":{"type":"texture","index":155,"assetRequest":{"type":"slide","state":"incoming","slide":"B8503B93-F3A5-4410-BAB5-20EC01F385C1"},"url":"assets/7055B3A55E23A029736BDFE481D0DA87.svg","width":1024,"height":768},"560B5ADB62380A2B775A7FFBDEF0A0E2":{"type":"texture","index":154,"assetRequest":{"type":"slide","state":"outgoing","slide":"F2C07866-FAE6-40C8-AA5A-CEA6FC6F3CAA"},"url":"assets/560B5ADB62380A2B775A7FFBDEF0A0E2.svg","width":1024,"height":768},"498E23C82CA78A4BCD7BA88E5243B6FC":{"type":"texture","index":149,"assetRequest":{"type":"slide","state":"contents","slide":"F2C07866-FAE6-40C8-AA5A-CEA6FC6F3CAA"},"url":"assets/498E23C82CA78A4BCD7BA88E5243B6FC.svg","width":1024,"height":768}},"events":[{"effects":[{"beginTime":0,"baseLayer":{"animations":[],"initialState":{"affineTransform":[1,0,0,1,0,0],"masksToBounds":false,"rotation":0,"scale":1,"position":{"pointX":506.7180633544922,"pointY":300},"width":813.4361267089844,"sublayerTransform":[1,0,0,0,0,1,0,0,0,0,1,0,0,0,0,1],"contentsRect":{"y":0,"x":0,"width":1,"height":1},"opacity":1,"edgeAntialiasingMask":15,"height":80.0000011920929,"hidden":false,"anchorPoint":{"pointX":0.5,"pointY":0.5}},"objectID":"0633391F-784A-49AC-A17F-0794EC43DE9F","layers":[{"animations":[],"initialState":{"affineTransform":[1,0,0,1,0,0],"masksToBounds":false,"rotation":0,"scale":1,"position":{"pointX":412,"pointY":124.0000005960464},"width":813.4361267089844,"sublayerTransform":[1,0,0,0,0,1,0,0,0,0,1,-0.0004922987690640373,0,0,0,1],"contentsRect":{"y":0,"x":0,"width":1,"height":1},"opacity":1,"edgeAntialiasingMask":15,"height":80.0000011920929,"hidden":false,"anchorPoint":{"pointX":0.5064933637345044,"pointY":1.549999984353781}},"layers":[{"animations":[{"repeatCount":0,"animations":[{"from":{"scalar":0},"beginTime":0,"repeatCount":0,"fillMode":"both","property":"opacity","duration":1,"timingFunction":"easeInEaseOut","to":{"scalar":1}},{"from":{"scalar":false},"beginTime":0,"repeatCount":0,"fillMode":"forwards","property":"hidden","duration":1,"to":{"scalar":false}}],"beginTime":1e-100,"fillMode":"both","duration":1}],"layers":[],"initialState":{"affineTransform":[1,0,0,1,0,0],"masksToBounds":false,"rotation":0,"scale":1,"position":{"pointX":192,"pointY":45.00000059604645},"width":376,"sublayerTransform":[1,0,0,0,0,1,0,0,0,0,1,0,0,0,0,1],"contentsRect":{"y":0,"x":0,"width":1,"height":1},"opacity":1,"edgeAntialiasingMask":0,"height":62,"hidden":true,"anchorPoint":{"pointX":0.5,"pointY":0.5}},"texture":"B653AF1AB0499FFDC5457C5AA168816F"}]}]},"effects":[{"beginTime":0,"baseLayer":{"animations":[],"initialState":{"affineTransform":[1,0,0,1,0,0],"masksToBounds":false,"rotation":0,"scale":1,"position":{"pointX":565.418701171875,"pointY":419.8726196289062},"width":813.4361267089844,"sublayerTransform":[1,0,0,0,0,1,0,0,0,0,1,0,0,0,0,1],"contentsRect":{"y":0,"x":0,"width":1,"height":1},"opacity":1,"edgeAntialiasingMask":15,"height":57.99999833106995,"hidden":false,"anchorPoint":{"pointX":0.5,"pointY":0.5}},"objectID":"3699E999-88CE-4DC7-97B4-3B8EE041A986","layers":[{"animations":[],"initialState":{"affineTransform":[1,0,0,1,0,0],"masksToBounds":false,"rotation":0,"scale":1,"position":{"pointX":353.2993621826172,"pointY":-6.872620463371277},"width":813.4361267089844,"sublayerTransform":[1,0,0,0,0,1,0,0,0,0,1,-0.0004922987690640373,0,0,0,1],"contentsRect":{"y":0,"x":0,"width":1,"height":1},"opacity":1,"edgeAntialiasingMask":15,"height":57.99999833106995,"hidden":false,"anchorPoint":{"pointX":0.4343295688279823,"pointY":-0.1184934596746306}},"layers":[{"animations":[{"repeatCount":0,"animations":[{"from":{"scalar":0},"beginTime":0,"repeatCount":0,"fillMode":"both","property":"opacity","duration":1,"timingFunction":"easeInEaseOut","to":{"scalar":1}},{"from":{"scalar":false},"beginTime":0,"repeatCount":0,"fillMode":"forwards","property":"hidden","duration":1,"to":{"scalar":false}}],"beginTime":1e-100,"fillMode":"both","duration":1}],"layers":[],"initialState":{"affineTransform":[1,0,0,1,0,0],"masksToBounds":false,"rotation":0,"scale":1,"position":{"pointX":355.7993621826172,"pointY":32.62737953662872},"width":705,"sublayerTransform":[1,0,0,0,0,1,0,0,0,0,1,0,0,0,0,1],"contentsRect":{"y":0,"x":0,"width":1,"height":1},"opacity":1,"edgeAntialiasingMask":0,"height":43,"hidden":true,"anchorPoint":{"pointX":0.5,"pointY":0.5}},"texture":"8E23504498D2CB49AC5BDD729BEB3B61"}]}]},"effects":[{"beginTime":0,"baseLayer":{"animations":[],"initialState":{"affineTransform":[1,0,0,1,0,0],"masksToBounds":false,"rotation":0,"scale":1,"position":{"pointX":565.418701171875,"pointY":495.0955505371094},"width":813.4361267089844,"sublayerTransform":[1,0,0,0,0,1,0,0,0,0,1,0,0,0,0,1],"contentsRect":{"y":0,"x":0,"width":1,"height":1},"opacity":1,"edgeAntialiasingMask":15,"height":57.99999833106995,"hidden":false,"anchorPoint":{"pointX":0.5,"pointY":0.5}},"objectID":"989FE361-A9C3-4FD3-8518-A3EDA7AD953D","layers":[{"animations":[],"initialState":{"affineTransform":[1,0,0,1,0,0],"masksToBounds":false,"rotation":0,"scale":1,"position":{"pointX":353.2993621826172,"pointY":-82.0955513715744},"width":813.4361267089844,"sublayerTransform":[1,0,0,0,0,1,0,0,0,0,1,-0.0004922987690640373,0,0,0,1],"contentsRect":{"y":0,"x":0,"width":1,"height":1},"opacity":1,"edgeAntialiasingMask":15,"height":57.99999833106995,"hidden":false,"anchorPoint":{"pointX":0.4343295688279823,"pointY":-1.41544058161803}},"layers":[{"animations":[{"repeatCount":0,"animations":[{"from":{"scalar":0},"beginTime":0,"repeatCount":0,"fillMode":"both","property":"opacity","duration":1,"timingFunction":"easeInEaseOut","to":{"scalar":1}},{"from":{"scalar":false},"beginTime":0,"repeatCount":0,"fillMode":"forwards","property":"hidden","duration":1,"to":{"scalar":false}}],"beginTime":1e-100,"fillMode":"both","duration":1}],"layers":[],"initialState":{"affineTransform":[1,0,0,1,0,0],"masksToBounds":false,"rotation":0,"scale":1,"position":{"pointX":391.7993621826172,"pointY":33.9044486284256},"width":777,"sublayerTransform":[1,0,0,0,0,1,0,0,0,0,1,0,0,0,0,1],"contentsRect":{"y":0,"x":0,"width":1,"height":1},"opacity":1,"edgeAntialiasingMask":0,"height":44,"hidden":true,"anchorPoint":{"pointX":0.5,"pointY":0.5}},"texture":"D26118405F285ECE109EB9C3B52B2A31"}]}]},"effects":[],"duration":1,"type":"buildIn","name":"apple:dissolve character","objectID":"989FE361-A9C3-4FD3-8518-A3EDA7AD953D"}],"duration":1,"type":"buildIn","name":"apple:dissolve character","objectID":"3699E999-88CE-4DC7-97B4-3B8EE041A986"}],"duration":1,"type":"buildIn","name":"apple:dissolve character","objectID":"0633391F-784A-49AC-A17F-0794EC43DE9F"}],"automaticPlay":true,"hyperlinks":[],"accessibility":[{"text":"Mohlo by vás zajímat","targetRectangle":{"y":81.99999991117738,"x":136.36,"width":751.2800000000002,"height":96}}],"baseLayer":{"animations":[],"initialState":{"affineTransform":[1,0,0,1,0,0],"masksToBounds":true,"rotation":0,"scale":1,"position":{"pointX":512,"pointY":384},"width":1024,"sublayerTransform":[1,0,0,0,0,1,0,0,0,0,1,0,0,0,0,1],"contentsRect":{"y":0,"x":0,"width":1,"height":1},"opacity":1,"edgeAntialiasingMask":0,"height":768,"hidden":false,"anchorPoint":{"pointX":0.5,"pointY":0.5}},"layers":[{"animations":[],"initialState":{"affineTransform":[1,0,0,1,0,0],"masksToBounds":false,"rotation":0,"scale":1,"position":{"pointX":512,"pointY":384},"width":1024,"sublayerTransform":[1,0,0,0,0,1,0,0,0,0,1,0,0,0,0,1],"contentsRect":{"y":0,"x":0,"width":1,"height":1},"opacity":1,"edgeAntialiasingMask":15,"height":768,"hidden":false,"anchorPoint":{"pointX":0.5,"pointY":0.5}},"layers":[{"animations":[],"initialState":{"affineTransform":[1,0,0,1,0,0],"masksToBounds":false,"rotation":0,"scale":1,"position":{"pointX":512,"pointY":384},"width":1024,"sublayerTransform":[1,0,0,0,0,1,0,0,0,0,1,0,0,0,0,1],"contentsRect":{"y":0,"x":0,"width":1,"height":1},"opacity":1,"edgeAntialiasingMask":15,"height":768,"hidden":false,"anchorPoint":{"pointX":0.5,"pointY":0.5}},"layers":[{"animations":[],"layers":[],"initialState":{"affineTransform":[1,0,0,1,0,0],"masksToBounds":false,"rotation":0,"scale":1,"position":{"pointX":512,"pointY":384},"width":1024,"sublayerTransform":[1,0,0,0,0,1,0,0,0,0,1,0,0,0,0,1],"contentsRect":{"y":0,"x":0,"width":1,"height":1},"opacity":1,"edgeAntialiasingMask":0,"height":768,"hidden":false,"anchorPoint":{"pointX":0.5,"pointY":0.5}},"texture":"498E23C82CA78A4BCD7BA88E5243B6FC"}]}]},{"animations":[],"initialState":{"affineTransform":[1,0,0,1,0,0],"masksToBounds":false,"rotation":0,"scale":1,"position":{"pointX":512,"pointY":384},"width":1024,"sublayerTransform":[1,0,0,0,0,1,0,0,0,0,1,0,0,0,0,1],"contentsRect":{"y":0,"x":0,"width":1,"height":1},"opacity":1,"edgeAntialiasingMask":15,"height":768,"hidden":false,"anchorPoint":{"pointX":0.5,"pointY":0.5}},"layers":[{"animations":[],"initialState":{"affineTransform":[1,0,0,1,0,0],"masksToBounds":false,"rotation":0,"scale":1,"position":{"pointX":512,"pointY":129.9999999111774},"width":824,"sublayerTransform":[1,0,0,0,0,1,0,0,0,0,1,0,0,0,0,1],"contentsRect":{"y":0,"x":0,"width":1,"height":1},"opacity":1,"edgeAntialiasingMask":15,"height":260,"hidden":false,"anchorPoint":{"pointX":0.5,"pointY":0.5}},"objectID":"D668CD5D-FE87-477B-8CA3-E0C28EF2A5C1","layers":[{"animations":[],"layers":[],"initialState":{"affineTransform":[1,0,0,1,0,0],"masksToBounds":false,"rotation":0,"scale":1,"position":{"pointX":414,"pointY":138.5000000888226},"width":746,"sublayerTransform":[1,0,0,0,0,1,0,0,0,0,1,0,0,0,0,1],"contentsRect":{"y":0,"x":0,"width":1,"height":1},"opacity":1,"edgeAntialiasingMask":0,"height":77,"hidden":false,"anchorPoint":{"pointX":0.5,"pointY":0.5}},"texture":"5C5CA35AF699D3D54CAEBA3659D3D590"}]}]},{"animations":[],"initialState":{"affineTransform":[1,0,0,1,0,0],"masksToBounds":false,"rotation":0,"scale":1,"position":{"pointX":512,"pointY":384},"width":1024,"sublayerTransform":[1,0,0,0,0,1,0,0,0,0,1,0,0,0,0,1],"contentsRect":{"y":0,"x":0,"width":1,"height":1},"opacity":1,"edgeAntialiasingMask":15,"height":768,"hidden":false,"anchorPoint":{"pointX":0.5,"pointY":0.5}},"layers":[{"animations":[],"initialState":{"affineTransform":[1,0,0,1,0,0],"masksToBounds":false,"rotation":0,"scale":1,"position":{"pointX":506.7180633544922,"pointY":300},"width":813.4361267089844,"sublayerTransform":[1,0,0,0,0,1,0,0,0,0,1,0,0,0,0,1],"contentsRect":{"y":0,"x":0,"width":1,"height":1},"opacity":1,"edgeAntialiasingMask":15,"height":80.0000011920929,"hidden":false,"anchorPoint":{"pointX":0.5,"pointY":0.5}},"objectID":"0633391F-784A-49AC-A17F-0794EC43DE9F","layers":[{"animations":[],"layers":[],"initialState":{"affineTransform":[1,0,0,1,0,0],"masksToBounds":false,"rotation":0,"scale":1,"position":{"pointX":192,"pointY":45.00000059604645},"width":376,"sublayerTransform":[1,0,0,0,0,1,0,0,0,0,1,0,0,0,0,1],"contentsRect":{"y":0,"x":0,"width":1,"height":1},"opacity":1,"edgeAntialiasingMask":0,"height":62,"hidden":true,"anchorPoint":{"pointX":0.5,"pointY":0.5}},"texture":"B653AF1AB0499FFDC5457C5AA168816F"}]}]},{"animations":[],"initialState":{"affineTransform":[1,0,0,1,0,0],"masksToBounds":false,"rotation":0,"scale":1,"position":{"pointX":512,"pointY":384},"width":1024,"sublayerTransform":[1,0,0,0,0,1,0,0,0,0,1,0,0,0,0,1],"contentsRect":{"y":0,"x":0,"width":1,"height":1},"opacity":1,"edgeAntialiasingMask":15,"height":768,"hidden":false,"anchorPoint":{"pointX":0.5,"pointY":0.5}},"layers":[{"animations":[],"initialState":{"affineTransform":[1,0,0,1,0,0],"masksToBounds":false,"rotation":0,"scale":1,"position":{"pointX":565.418701171875,"pointY":419.8726196289062},"width":813.4361267089844,"sublayerTransform":[1,0,0,0,0,1,0,0,0,0,1,0,0,0,0,1],"contentsRect":{"y":0,"x":0,"width":1,"height":1},"opacity":1,"edgeAntialiasingMask":15,"height":57.99999833106995,"hidden":false,"anchorPoint":{"pointX":0.5,"pointY":0.5}},"objectID":"3699E999-88CE-4DC7-97B4-3B8EE041A986","layers":[{"animations":[],"layers":[],"initialState":{"affineTransform":[1,0,0,1,0,0],"masksToBounds":false,"rotation":0,"scale":1,"position":{"pointX":355.7993621826172,"pointY":32.62737953662872},"width":705,"sublayerTransform":[1,0,0,0,0,1,0,0,0,0,1,0,0,0,0,1],"contentsRect":{"y":0,"x":0,"width":1,"height":1},"opacity":1,"edgeAntialiasingMask":0,"height":43,"hidden":true,"anchorPoint":{"pointX":0.5,"pointY":0.5}},"texture":"8E23504498D2CB49AC5BDD729BEB3B61"}]}]},{"animations":[],"initialState":{"affineTransform":[1,0,0,1,0,0],"masksToBounds":false,"rotation":0,"scale":1,"position":{"pointX":512,"pointY":384},"width":1024,"sublayerTransform":[1,0,0,0,0,1,0,0,0,0,1,0,0,0,0,1],"contentsRect":{"y":0,"x":0,"width":1,"height":1},"opacity":1,"edgeAntialiasingMask":15,"height":768,"hidden":false,"anchorPoint":{"pointX":0.5,"pointY":0.5}},"layers":[{"animations":[],"initialState":{"affineTransform":[1,0,0,1,0,0],"masksToBounds":false,"rotation":0,"scale":1,"position":{"pointX":565.418701171875,"pointY":495.0955505371094},"width":813.4361267089844,"sublayerTransform":[1,0,0,0,0,1,0,0,0,0,1,0,0,0,0,1],"contentsRect":{"y":0,"x":0,"width":1,"height":1},"opacity":1,"edgeAntialiasingMask":15,"height":57.99999833106995,"hidden":false,"anchorPoint":{"pointX":0.5,"pointY":0.5}},"objectID":"989FE361-A9C3-4FD3-8518-A3EDA7AD953D","layers":[{"animations":[],"layers":[],"initialState":{"affineTransform":[1,0,0,1,0,0],"masksToBounds":false,"rotation":0,"scale":1,"position":{"pointX":391.7993621826172,"pointY":33.9044486284256},"width":777,"sublayerTransform":[1,0,0,0,0,1,0,0,0,0,1,0,0,0,0,1],"contentsRect":{"y":0,"x":0,"width":1,"height":1},"opacity":1,"edgeAntialiasingMask":0,"height":44,"hidden":true,"anchorPoint":{"pointX":0.5,"pointY":0.5}},"texture":"D26118405F285ECE109EB9C3B52B2A31"}]}]}]}},{"effects":[{"beginTime":0,"baseLayer":{"animations":[],"initialState":{"affineTransform":[1,0,0,1,0,0],"masksToBounds":true,"rotation":0,"scale":1,"position":{"pointX":512,"pointY":384},"width":1024,"sublayerTransform":[1,0,0,0,0,1,0,0,0,0,1,0,0,0,0,1],"contentsRect":{"y":0,"x":0,"width":1,"height":1},"opacity":1,"edgeAntialiasingMask":0,"height":768,"hidden":false,"anchorPoint":{"pointX":0.5,"pointY":0.5}},"objectID":"0","layers":[{"animations":[],"initialState":{"affineTransform":[1,0,0,1,0,0],"masksToBounds":false,"rotation":0,"scale":1,"position":{"pointX":512,"pointY":384},"width":1024,"sublayerTransform":[1,0,0,0,0,1,0,0,0,0,1,-0.0004922987690640373,0,0,0,1],"contentsRect":{"y":0,"x":0,"width":1,"height":1},"opacity":1,"edgeAntialiasingMask":15,"height":768,"hidden":false,"anchorPoint":{"pointX":0.5,"pointY":0.5}},"layers":[{"animations":[{"repeatCount":0,"animations":[{"repeatCount":0,"timingControlPoint2y":1,"from":{"scalar":-4096},"timingFunction":"custom","timingControlPoint1x":0.2972677648067474,"property":"transform.translation.z","fillMode":"removed","duration":2,"beginTime":0,"timingControlPoint2x":0.6975351572036743,"timingControlPoint1y":0,"to":{"scalar":0}},{"from":{"scalar":0.1},"beginTime":0,"repeatCount":0,"fillMode":"removed","property":"opacity","duration":2,"timingFunction":"easeIn","to":{"scalar":1}}],"beginTime":0,"fillMode":"both","duration":2}],"layers":[{"animations":[],"layers":[],"initialState":{"affineTransform":[1,0,0,1,0,0],"masksToBounds":false,"rotation":0,"scale":1,"position":{"pointX":512,"pointY":1056},"width":1024,"sublayerTransform":[1,0,0,0,0,1,0,0,0,0,1,0,0,0,0,1],"contentsRect":{"y":0,"x":0,"width":1,"height":1},"opacity":1,"edgeAntialiasingMask":15,"height":576,"hidden":false,"anchorPoint":{"pointX":0.5,"pointY":0.5}},"texture":"F99111D3C439758D4F9FFAA8EE22F8D5"}],"initialState":{"affineTransform":[1,0,0,1,0,0],"masksToBounds":false,"rotation":0,"scale":1,"position":{"pointX":512,"pointY":384},"width":1024,"sublayerTransform":[1,0,0,0,0,1,0,0,0,0,1,0,0,0,0,1],"contentsRect":{"y":0,"x":0,"width":1,"height":1},"opacity":1,"edgeAntialiasingMask":0,"height":768,"hidden":false,"anchorPoint":{"pointX":0.5,"pointY":0.5}},"texture":"7055B3A55E23A029736BDFE481D0DA87"},{"animations":[{"repeatCount":0,"animations":[{"from":{"scalar":1},"beginTime":0,"repeatCount":0,"fillMode":"both","property":"opacity","duration":0.01666666666666667,"to":{"scalar":0}}],"beginTime":0,"fillMode":"both","duration":2}],"layers":[],"initialState":{"affineTransform":[1,0,0,1,0,0],"masksToBounds":false,"rotation":0,"scale":1,"position":{"pointX":512,"pointY":384},"width":1024,"sublayerTransform":[1,0,0,0,0,1,0,0,0,0,1,0,0,0,0,1],"contentsRect":{"y":0,"x":0,"width":1,"height":1},"opacity":1,"edgeAntialiasingMask":0,"height":768,"hidden":false,"anchorPoint":{"pointX":0.5,"pointY":0.5}},"texture":"560B5ADB62380A2B775A7FFBDEF0A0E2"},{"animations":[{"repeatCount":0,"timingControlPoint2y":1,"from":{"scalar":1},"timingFunction":"custom","timingControlPoint1x":0.2972677648067474,"property":"transform.scale.xy","fillMode":"both","duration":2,"beginTime":0,"timingControlPoint2x":0.6975351572036743,"timingControlPoint1y":0,"to":{"scalar":2}}],"initialState":{"affineTransform":[1,0,0,1,0,0],"masksToBounds":false,"rotation":0,"scale":1,"position":{"pointX":512,"pointY":384},"width":1024,"sublayerTransform":[1,0,0,0,0,1,0,0,0,0,1,0,0,0,0,1],"contentsRect":{"y":0,"x":0,"width":1,"height":1},"opacity":1,"edgeAntialiasingMask":15,"height":768,"hidden":false,"anchorPoint":{"pointX":0.5,"pointY":0.5}},"layers":[{"animations":[{"repeatCount":0,"timingControlPoint2y":1,"from":{"scalar":0},"timingFunction":"custom","timingControlPoint1x":0.2972677648067474,"property":"transform.rotation.y","fillMode":"both","duration":2,"beginTime":0,"timingControlPoint2x":0.6975351572036743,"timingControlPoint1y":0,"to":{"scalar":2.199114857512855}}],"initialState":{"affineTransform":[1,0,0,1,0,0],"scale":1,"rotation":0,"masksToBounds":false,"position":{"pointX":0,"pointY":384},"backgroundColor":[0,0,0,1],"width":512,"sublayerTransform":[1,0,0,0,0,1,0,0,0,0,1,0,0,0,0,1],"contentsRect":{"y":0,"x":0,"width":1,"height":1},"opacity":1,"edgeAntialiasingMask":0,"height":768,"hidden":false,"anchorPoint":{"pointX":0,"pointY":0.5}},"layers":[{"animations":[{"repeatCount":0,"timingControlPoint2y":1,"from":{"scalar":1},"timingFunction":"custom","timingControlPoint1x":0.2972677648067474,"property":"opacity","fillMode":"both","duration":2,"beginTime":0,"timingControlPoint2x":0.6975351572036743,"timingControlPoint1y":0,"to":{"scalar":0}}],"layers":[],"initialState":{"affineTransform":[1,0,0,1,0,0],"masksToBounds":false,"rotation":0,"scale":1,"position":{"pointX":256,"pointY":384},"width":512,"sublayerTransform":[1,0,0,0,0,1,0,0,0,0,1,0,0,0,0,1],"contentsRect":{"y":0,"x":0,"width":0.5,"height":1},"opacity":1,"edgeAntialiasingMask":0,"height":768,"hidden":false,"anchorPoint":{"pointX":0.5,"pointY":0.5}},"texture":"560B5ADB62380A2B775A7FFBDEF0A0E2"}]},{"animations":[{"repeatCount":0,"timingControlPoint2y":1,"from":{"scalar":0},"timingFunction":"custom","timingControlPoint1x":0.2972677648067474,"property":"transform.rotation.y","fillMode":"both","duration":2,"beginTime":0,"timingControlPoint2x":0.6975351572036743,"timingControlPoint1y":0,"to":{"scalar":-2.199114857512855}}],"initialState":{"affineTransform":[1,0,0,1,0,0],"scale":1,"rotation":0,"masksToBounds":false,"position":{"pointX":1024,"pointY":384},"backgroundColor":[0,0,0,1],"width":512,"sublayerTransform":[1,0,0,0,0,1,0,0,0,0,1,0,0,0,0,1],"contentsRect":{"y":0,"x":0,"width":1,"height":1},"opacity":1,"edgeAntialiasingMask":0,"height":768,"hidden":false,"anchorPoint":{"pointX":1,"pointY":0.5}},"layers":[{"animations":[{"repeatCount":0,"timingControlPoint2y":1,"from":{"scalar":1},"timingFunction":"custom","timingControlPoint1x":0.2972677648067474,"property":"opacity","fillMode":"both","duration":2,"beginTime":0,"timingControlPoint2x":0.6975351572036743,"timingControlPoint1y":0,"to":{"scalar":0}}],"layers":[],"initialState":{"affineTransform":[1,0,0,1,0,0],"masksToBounds":false,"rotation":0,"scale":1,"position":{"pointX":256,"pointY":384},"width":512,"sublayerTransform":[1,0,0,0,0,1,0,0,0,0,1,0,0,0,0,1],"contentsRect":{"y":0,"x":0.5,"width":0.5,"height":1},"opacity":1,"edgeAntialiasingMask":0,"height":768,"hidden":false,"anchorPoint":{"pointX":0.5,"pointY":0.5}},"texture":"560B5ADB62380A2B775A7FFBDEF0A0E2"}]}]}]}]},"effects":[],"duration":2,"type":"transition","name":"apple:doorway","objectID":"0"}],"automaticPlay":false,"hyperlinks":[],"accessibility":[{"text":"Mohlo by vás zajímat","targetRectangle":{"y":81.99999991117738,"x":136.36,"width":751.2800000000002,"height":96}},{"text":"false negative ( nepřijetím správného )","targetRectangle":{"y":470.0955513715744,"x":221.0339739322662,"width":718.8719999999997,"height":50}},{"text":"false positive ( neodmítne špatné )","targetRectangle":{"y":394.8726204633713,"x":221.0339739322662,"width":646.5479999999999,"height":50}},{"text":"Chyby testů","targetRectangle":{"y":263.9999994039536,"x":162.3333325386047,"width":320.1,"height":72}}],"baseLayer":{"animations":[],"initialState":{"affineTransform":[1,0,0,1,0,0],"masksToBounds":true,"rotation":0,"scale":1,"position":{"pointX":512,"pointY":384},"width":1024,"sublayerTransform":[1,0,0,0,0,1,0,0,0,0,1,0,0,0,0,1],"contentsRect":{"y":0,"x":0,"width":1,"height":1},"opacity":1,"edgeAntialiasingMask":0,"height":768,"hidden":false,"anchorPoint":{"pointX":0.5,"pointY":0.5}},"objectID":"0","layers":[{"animations":[],"initialState":{"affineTransform":[1,0,0,1,0,0],"masksToBounds":false,"rotation":0,"scale":1,"position":{"pointX":512,"pointY":384},"width":1024,"sublayerTransform":[1,0,0,0,0,1,0,0,0,0,1,-0.0004922987690640373,0,0,0,1],"contentsRect":{"y":0,"x":0,"width":1,"height":1},"opacity":1,"edgeAntialiasingMask":15,"height":768,"hidden":false,"anchorPoint":{"pointX":0.5,"pointY":0.5}},"layers":[{"animations":[],"layers":[],"initialState":{"affineTransform":[1,0,0,1,0,0],"masksToBounds":false,"rotation":0,"scale":1,"position":{"pointX":512,"pointY":384},"width":1024,"sublayerTransform":[1,0,0,0,0,1,0,0,0,0,1,0,0,0,0,1],"contentsRect":{"y":0,"x":0,"width":1,"height":1},"opacity":1,"edgeAntialiasingMask":0,"height":768,"hidden":false,"anchorPoint":{"pointX":0.5,"pointY":0.5}},"texture":"560B5ADB62380A2B775A7FFBDEF0A0E2"}]}]}}]}